.coveragerc
.gitignore
.travis.yml
MANIFEST.in
README.rst
build_sublime_snippet.py
requirements.txt
setup.cfg
setup.py
tox.ini
docs/Makefile
docs/conf.py
docs/index.rst
docs/api/django.rst
docs/api/params.rst
docs/api/prepare.rst
docs/api/require/circus.rst
docs/api/require/git.rst
docs/api/require/nginx.rst
docs/api/require/releases_manager.rst
docs/api/require/system.rst
docs/api/require/databases/databases.rst
docs/api/require/databases/ldap.rst
docs/api/require/databases/mongodb.rst
docs/api/require/databases/mysql.rst
docs/api/require/databases/oracle.rst
docs/api/require/databases/postgres.rst
docs/api/require/databases/sqlite.rst
docs/api/require/django/command.rst
docs/api/require/django/utils.rst
docs/api/require/python/utils.rst
docs/api/require/python/virtualenv.rst
docs/examples/fabfiles/fabfile_nginx_circus_django.rst
docs/templates/app.ini.tpl.rst
docs/templates/circus.ini.tpl.rst
docs/templates/maintenance.html.tpl.rst
docs/templates/nginx.conf.tpl.rst
docs/templates/nginx_down.conf.tpl.rst
docs/templates/upstart.conf.tpl.rst
pydiploy/__init__.py
pydiploy/bottle.py
pydiploy/decorators.py
pydiploy/django.py
pydiploy/params.py
pydiploy/php.py
pydiploy/prepare.py
pydiploy/scripts.py
pydiploy/simple.py
pydiploy/version.py
pydiploy.egg-info/PKG-INFO
pydiploy.egg-info/SOURCES.txt
pydiploy.egg-info/dependency_links.txt
pydiploy.egg-info/entry_points.txt
pydiploy.egg-info/pbr.json
pydiploy.egg-info/requires.txt
pydiploy.egg-info/top_level.txt
pydiploy/examples/bottle_fabfile.py
pydiploy/examples/django_fabfile.py
pydiploy/examples/simple_fabfile.py
pydiploy/require/__init__.py
pydiploy/require/apache.py
pydiploy/require/circus.py
pydiploy/require/git.py
pydiploy/require/nginx.py
pydiploy/require/releases_manager.py
pydiploy/require/system.py
pydiploy/require/bottle/__init__.py
pydiploy/require/bottle/command.py
pydiploy/require/bottle/utils.py
pydiploy/require/databases/__init__.py
pydiploy/require/databases/ldap.py
pydiploy/require/databases/mongodb.py
pydiploy/require/databases/mysql.py
pydiploy/require/databases/oracle.py
pydiploy/require/databases/postgres.py
pydiploy/require/databases/sap.py
pydiploy/require/databases/sqlite.py
pydiploy/require/django/__init__.py
