Metadata-Version: 1.2
Name: pydiploy
Version: 1.2.0
Summary: A tool to deploy applications, and automate processing with fabric
Home-page: https://github.com/unistra/pydiploy
Author: di-dip-unistra
Author-email: di-dip@unistra.fr
Maintainer: di-dip-unistra
Maintainer-email: di-dip@unistra.fr
License: PSF
Download-URL: http://pypi.python.org/pypi/pydiploy
Keywords: deploy,fabric,automation
Platform: UNKNOWN
Classifier: Development Status :: 4 - Beta
Classifier: Intended Audience :: Developers
Classifier: License :: OSI Approved :: BSD License
Classifier: Operating System :: OS Independent
Classifier: Programming Language :: Python :: 2.7
